{
  "transferencias": [
    {
      "id": 1,
      "valor": 35,
      "destino": "1212-1",
      "data": "2020-11-06T21:34:17.155Z"
    },
    {
      "id": 2,
      "valor": 40,
      "destino": "1213-1",
      "data": "2020-11-06T21:24:10.710Z"
    },
    {
      "valor": "123123",
      "destino": "123123",
      "id": 3
    },
    {
      "valor": "123123",
      "destino": "123123123",
      "id": 4
    },
    {
      "valor": "23423434",
      "destino": "234",
      "data": "2022-01-24T19:13:38.286Z",
      "id": 5
    },
    {
      "valor": "1111",
      "destino": "12121212",
      "data": "2022-01-24T19:13:48.327Z",
      "id": 6
    },
    {
      "valor": "20",
      "destino": "121212",
      "data": "2022-01-24T19:13:57.112Z",
      "id": 7
    },
    {
      "valor": "200.00",
      "destino": "vitor",
      "data": "2022-01-24T19:14:20.182Z",
      "id": 8
    },
    {
      "valor": "123123123",
      "destino": "123123123",
      "data": "2022-01-24T19:15:21.011Z",
      "id": 9
    },
    {
      "valor": "3434.34",
      "destino": "234234",
      "data": "2022-01-24T19:15:46.970Z",
      "id": 10
    },
    {
      "valor": "123123",
      "destino": "123123",
      "data": "2022-01-25T11:51:25.125Z",
      "id": 11
    },
    {
      "valor": "12212",
      "destino": "344345",
      "data": "2022-01-25T12:24:00.687Z",
      "id": 12
    },
    {
      "valor": "1212",
      "destino": "1212",
      "data": "2022-01-25T12:26:37.075Z",
      "id": 13
    }
  ]
}